pymast/__init__.py
pymast/fish_history.py
pymast/formatter.py
pymast/naive_bayes.py
pymast/overlap_removal.py
pymast/parsers.py
pymast/predictors.py
pymast/radio_project.py
pymast/table_merge.py
pymast-0.0.6.dist-info/LICENSE.txt
pymast-0.0.6.dist-info/METADATA
pymast-0.0.6.dist-info/WHEEL
pymast-0.0.6.dist-info/top_level.txt
pymast-0.0.6.dist-info/RECORD
